[
  {
    "id": 1,
    "title": "Зустріч з автором: Марія Ковач",
    "date": "2024-04-15",
    "time": "18:00 - 20:00",
    "location": "Головна зала",
    "image": "https://images.unsplash.com/photo-1517971071642-34a2d3ecc9cd?ixlib=rb-1.2.1&auto=format&fit=crop&w=500&q=60",
    "description": "Приєднуйтесь до вечора з бестселером, автором Марією Ковач, яка представить свою нову книгу 'Ехо вічності'. Оформіть автограф і візьміть участь у захоплюючій сесії запитань та відповідей."
  },
  {
    "id": 2,
    "title": "Дитяче читання казок",
    "date": "2024-04-20",
    "time": "10:00 - 11:00",
    "location": "Дитячий куточок",
    "image": "https://images.unsplash.com/photo-1544716278-ca5e3f4abd8c?ixlib=rb-1.2.1&auto=format&fit=crop&w=500&q=60",
    "description": "Запрошуємо малечу на чарівне читання казок. Наш досвідчений ведучий розповість улюблені казки, розвиваючи фантазію та любов до читання."
  },
  {
    "id": 3,
    "title": "Книжковий клуб: 'Тихий Ехо'",
    "date": "2024-04-25",
    "time": "19:00 - 21:00",
    "location": "Читальний зал",
    "image": "https://images.unsplash.com/photo-1532012197267-da84d127e765?ixlib=rb-1.2.1&auto=format&fit=crop&w=500&q=60",
    "description": "Пориньте у глибоке обговорення книжки цього місяця — 'Тихий Ехо' Дж. К. Роулінг. Поділіться своїми думками з іншими любителями книг."
  },
  {
    "id": 5,
    "title": "Майстер-клас з графічних романів",
    "date": "2024-05-10",
    "time": "14:00 - 16:00",
    "location": "Мистецька зала",
    "image": "https://www.cartoonstudies.org/wp-content/uploads/2014/04/9314067529_f4c608596d_o.jpg",
    "description": "Приєднуйтесь до творчого майстер-класу, де ви дізнаєтесь, як створювати власний графічний роман. Матеріали будуть надані."
  },
  {
    "id": 6,
    "title": "Ярмарок фантастичних книг",
    "date": "2024-06-01",
    "time": "09:00 - 18:00",
    "location": "Громадський центр",
    "image": "https://images.pexels.com/photos/3987020/pexels-photo-3987020.jpeg?auto=compress&cs=tinysrgb&dpr=2&h=750&w=1260",
    "description": "Святкуйте світ фантастичної літератури з авторами, художниками та видавцями. Участь у панелях, автограф-сесіях та майстер-класах."
  },
  {
    "id": 7,
    "title": "Містерійний вечір: Полювання за підказками",
    "date": "2024-06-15",
    "time": "18:30 - 20:30",
    "location": "Сад бібліотеки",
    "image": "https://images.pexels.com/photos/28969936/pexels-photo-28969936.jpeg?auto=compress&cs=tinysrgb&dpr=2&h=750&w=1260",
    "description": "Приєднуйтесь до інтерактивного полювання за підказками в саду бібліотеки. Зберіть друзів і вирішуйте загадки разом!"
  },
  {
    "id": 8,
    "title": "Самвидав 101",
    "date": "2024-06-20",
    "time": "16:00 - 18:00",
    "location": "Конференц-зал",
    "image": "https://images.pexels.com/photos/20360855/pexels-photo-20360855.jpeg?auto=compress&cs=tinysrgb&dpr=2&h=750&w=1260",
    "description": "Дізнайтеся все про самвидав від експертів індустрії. Ідеально для початківців авторів, які хочуть опублікувати свої книги."
  }
]
